stnmf/__init__.py
stnmf/core.py
stnmf/init.py
stnmf/mf.py
stnmf/nnls.py
stnmf/plot.py
stnmf/spatial.py
stnmf/util.py
stnmf/callbacks/__init__.py
stnmf/callbacks/consensus.py
stnmf/callbacks/perturbation.py
stnmf/callbacks/residual.py
stnmf/callbacks/stopping_criterion.py
stnmf/preprocessing/__init__.py
stnmf/preprocessing/spiketriggered.py
stnmf-1.1.0.dist-info/LICENSE
stnmf-1.1.0.dist-info/METADATA
stnmf-1.1.0.dist-info/WHEEL
stnmf-1.1.0.dist-info/top_level.txt
stnmf-1.1.0.dist-info/RECORD
