Metadata-Version: 2.1
Name: stnmf
Version: 1.1.0
Summary: Fast and versatile implementation of spike-triggered non-negative matrix factorization based on AF-HALS
Author: Sören J. Zapp, Tim Gollisch
License: MIT
Project-URL: Documentation, https://stnmf.readthedocs.io
Project-URL: Repository, https://github.com/gollischlab/STNMF_with_AFHALS.git
Project-URL: Issues, https://github.com/gollischlab/STNMF_with_AFHALS/issues
Keywords: retina,subunits,primate,receptive field,neuroscience,STNMF,NMF,NNSVD-LRC,HALS
Classifier: Intended Audience :: Science/Research
Classifier: Operating System :: OS Independent
Classifier: Topic :: Scientific/Engineering
Requires-Python: >=3.10
License-File: LICENSE
Requires-Dist: cycler >=0.12.1
Requires-Dist: matplotlib >=3.7.0
Requires-Dist: numpy <=2.1.1,>=1.22.0
Requires-Dist: scikit-image >=0.22.0
Requires-Dist: scipy >=1.11.0
Requires-Dist: shapely >=2.0.0
Requires-Dist: tqdm >=4.66.1
